<web-service> 

    <display-name>Web Services para CRM</display-name> 
    <destination-path>d:\Deploy/CustomerRelationshipManagementWSEAR.ear</destination-path> 
    <temporary-directory>D:\DEPLOY/TMP_WS/CusRelManWS</temporary-directory> 
    <context>/CustomerRelationshipManagementWSEAR</context> 

    <stateless-session-ejb-service> 
        <path>D:\DEPLOY/TMP_WS/CusRelManWS/ejb</path>         
        <uri>CusRelManWSFacade</uri> 
        <ejb-name>CusRelManWSFacade</ejb-name> 
    </stateless-session-ejb-service> 

</web-service> 